api/__init__.py
api/add.py
api/subtract.py
core/__init__.py
core/add.py
core/subtract.py
pmps-0.2.dist-info/LICENSE
pmps-0.2.dist-info/METADATA
pmps-0.2.dist-info/WHEEL
pmps-0.2.dist-info/top_level.txt
pmps-0.2.dist-info/RECORD
