Metadata-Version: 2.1
Name: pmps
Version: 0.2
Summary: A small example package
Home-page: https://github.com/samysung/python_ml_project_skeleton
Author: samy khelifi
Author-email: samy.khelifi@ign.fr
Project-URL: Bug Tracker, https://github.com/samysung/python_ml_project_skeleton/issues
Classifier: Programming Language :: Python :: 3
Classifier: Programming Language :: Python :: 3.9
Classifier: Programming Language :: Python :: 3.10
Classifier: License :: OSI Approved :: Apache Software License
Classifier: Operating System :: OS Independent
Classifier: Topic :: Scientific/Engineering :: Artificial Intelligence
Requires-Python: >=3.9
License-File: LICENSE
Requires-Dist: geopandas (>=0.10)
Requires-Dist: rasterio (>=1.1.5)
